sbmodder/__init__.py
sbmodder/client.py
sbmodder-0.1.1.dist-info/entry_points.txt
sbmodder-0.1.1.dist-info/WHEEL
sbmodder-0.1.1.dist-info/METADATA
sbmodder-0.1.1.dist-info/RECORD
