Metadata-Version: 2.1
Name: sbmodder
Version: 0.1.1
Summary: Tool to manage git submodule
Author: takumi2786
Author-email: takumi_1884@icloud.com
Requires-Python: >=3.7,<4.0
Classifier: Programming Language :: Python :: 3
Classifier: Programming Language :: Python :: 3.10
Classifier: Programming Language :: Python :: 3.7
Classifier: Programming Language :: Python :: 3.8
Classifier: Programming Language :: Python :: 3.9
Requires-Dist: GitPython (>=3.1.27,<4.0.0)
Requires-Dist: fire (>=0.4.0,<0.5.0)
